README.rst
dicty.py
setup.cfg
setup.py
dicty.egg-info/PKG-INFO
dicty.egg-info/SOURCES.txt
dicty.egg-info/dependency_links.txt
dicty.egg-info/requires.txt
dicty.egg-info/top_level.txt