Metadata-Version: 1.0
Name: dicty
Version: 0.1.1
Summary: A library for mapping dictionaries to Python objects
Home-page: https://github.com/vitek/dicty
Author: Victor Makarov
Author-email: vitja.makarov@gmail.com
License: UNKNOWN
Platform: UNKNOWN
